LICENSE
floc_simhash/__init__.py
floc_simhash/text/__init__.py
floc_simhash/text/simhash.py
floc_simhash/text/sorting.py
floc_simhash/transformer/geometric.py
floc_simhash-0.1.0.dist-info/LICENSE
floc_simhash-0.1.0.dist-info/WHEEL
floc_simhash-0.1.0.dist-info/METADATA
floc_simhash-0.1.0.dist-info/RECORD
