Metadata-Version: 2.1
Name: floc-simhash
Version: 0.1.0
Summary: A fast python implementation of the SimHash algorithm
Home-page: https://github.com/hybridtheory/floc-simhash
License: MIT
Keywords: floc,simhash
Author: Engineering
Author-email: engineering@hybridtheory.com
Requires-Python: >=3.7,<4
Classifier: License :: OSI Approved :: MIT License
Classifier: Programming Language :: Python :: 3
Classifier: Programming Language :: Python :: 3.7
Classifier: Programming Language :: Python :: 3.8
Classifier: Programming Language :: Python :: 3.9
Classifier: Topic :: Software Development :: Libraries :: Python Modules
Requires-Dist: scikit-learn (>=0.24.1,<0.25.0)
Project-URL: Repository, https://github.com/hybridtheory/floc-simhash
